fulladd/fulladd.v
// フルアダー
module fulladd(A, B, CIN, Q, COUT);
input A, B, CIN;
output Q, COUT;

assign Q = A ^ B ^ CIN;
assign COUT = A & B | B & CIN | CIN & A;

endmodule

fulladd/fulladd_tp.v
`timescale 1ps/1ps

// |---|----|------|------|-------|
// | A |  B |  CIN |  Q   |  COUT |
// |---|----|------|------|-------|
// | 0 |  0 |  0   |    0 |  0    |
// |---|----|------|------|-------|
// | 0 |  0 |  1   |    1 |  0    |
// |---|----|------|------|-------|
// | 0 |  1 |  0   |    1 |  0    |
// |---|----|------|------|-------|
// | 0 |  1 |  1   |    0 |  1    |
// |---|----|------|------|-------|
// | 1 |  0 |  0   |    1 |  0    |
// |---|----|------|------|-------|
// | 1 |  0 |  1   |    0 |  1    |
// |---|----|------|------|-------|
// | 1 |  1 |  0   |    0 |  1    |
// |---|----|------|------|-------|
// | 1 |  1 |  1   |    1 |  1    |
// |---|----|------|------|-------|

module fulladd_tp;

reg A, B, CIN;
wire Q, COUT;

// シミュレーションステップの設定
parameter STEP = 100000;

// テスト対象インスタンス
fulladd fulladd(A, B, CIN, Q, COUT);

// テスト入力
initial begin
    // VCDファイル出力
    $dumpfile("fulladd.vcd");
    $dumpvars(0, fulladd_tp);

          A = 1'b0; B = 1'b0; CIN = 1'b0; // 0 + 0 + 0 -> Q = 0, COUT = 0
    #STEP A = 1'b0; B = 1'b0; CIN = 1'b1; // 0 + 0 + 1 -> Q = 1, COUT = 0
    #STEP A = 1'b0; B = 1'b1; CIN = 1'b0; // 0 + 1 + 0 -> Q = 1, COUT = 0
    #STEP A = 1'b0; B = 1'b1; CIN = 1'b1; // 0 + 1 + 1 -> Q = 0, COUT = 1
    #STEP A = 1'b1; B = 1'b0; CIN = 1'b0; // 1 + 0 + 0 -> Q = 1, COUT = 0
    #STEP A = 1'b1; B = 1'b0; CIN = 1'b1; // 1 + 0 + 1 -> Q = 0, COUT = 1
    #STEP A = 1'b1; B = 1'b1; CIN = 1'b0; // 1 + 1 + 0 -> Q = 0, COUT = 1
    #STEP A = 1'b1; B = 1'b1; CIN = 1'b1; // 1 + 1 + 1 -> Q = 1, COUT = 1
    #STEP $finish;
end

// コンソール出力
initial $monitor($stime, " A=%b B=%b CIN=%b Q=%b COUT=%b", A, B, CIN, Q, COUT);

endmodule

fulladd/fulladd.vcd
$date
	Fri Apr 18 14:20:10 2025
$end
$version
	Icarus Verilog
$end
$timescale
	1ps
$end
$scope module fulladd_tp $end
$var wire 1 ! Q $end
$var wire 1 " COUT $end
$var parameter 32 # STEP $end
$var reg 1 $ A $end
$var reg 1 % B $end
$var reg 1 & CIN $end
$scope module fulladd $end
$var wire 1 $ A $end
$var wire 1 % B $end
$var wire 1 & CIN $end
$var wire 1 " COUT $end
$var wire 1 ! Q $end
$upscope $end
$upscope $end
$enddefinitions $end
$comment Show the parameter values. $end
$dumpall
b11000011010100000 #
$end
#0
$dumpvars
0&
0%
0$
0"
0!
$end
#100000
1!
1&
#200000
0&
1%
#300000
1"
0!
1&
#400000
0"
1!
0&
0%
1$
#500000
1"
0!
1&
#600000
0&
1%
#700000
1!
1&
